pynondimensionalizer/__init__.py
pynondimensionalizer/pynondimensionalizer.py
tests/__init__.py
tests/test_pynondimensionalizer.py
PyNondimensionalizer-0.2.0.dist-info/LICENSE
PyNondimensionalizer-0.2.0.dist-info/METADATA
PyNondimensionalizer-0.2.0.dist-info/WHEEL
PyNondimensionalizer-0.2.0.dist-info/entry_points.txt
PyNondimensionalizer-0.2.0.dist-info/top_level.txt
PyNondimensionalizer-0.2.0.dist-info/RECORD
