Metadata-Version: 2.1
Name: PyNondimensionalizer
Version: 0.2.0
Summary: A command line program that calculates the nullspace vector from a given dimensional matrix.
Author: Doug Keller <dg.kllr.jr@gmail.com>
License: MIT License
Project-URL: Repository, https://github.com/dkllrjr/PyNondimensionalizer
Project-URL: Homepage, https://www.alaskanresearcher.dev/PyNondimensionalizer/pynondimensionalizer.html
License-File: LICENSE
Requires-Dist: click
Requires-Dist: sympy
Requires-Dist: pandas
